Metadata-Version: 2.1
Name: quaxa
Version: 0.1.1
Summary: QUAlity of sentence eXAmples scoring
Home-page: http://github.com/ulf1/quaxa
Author: Ulf Hamster
Author-email: 554c46@gmail.com
License: Apache License 2.0
Platform: UNKNOWN
Requires-Python: >=3.7
License-File: LICENSE
